constructs/__init__.py
constructs/py.typed
constructs/_jsii/__init__.py
constructs/_jsii/constructs@10.4.3.jsii.tgz
constructs-10.4.3.dist-info/LICENSE
constructs-10.4.3.dist-info/METADATA
constructs-10.4.3.dist-info/NOTICE
constructs-10.4.3.dist-info/WHEEL
constructs-10.4.3.dist-info/top_level.txt
constructs-10.4.3.dist-info/RECORD
